ocrvid/__init__.py
ocrvid/__main__.py
ocrvid/cli.py
ocrvid/config.py
ocrvid/ocr.py
ocrvid/video.py
ocrvid-0.5.3.dist-info/LICENSE
ocrvid-0.5.3.dist-info/METADATA
ocrvid-0.5.3.dist-info/WHEEL
ocrvid-0.5.3.dist-info/entry_points.txt
ocrvid-0.5.3.dist-info/top_level.txt
ocrvid-0.5.3.dist-info/RECORD
