Metadata-Version: 2.1
Name: ocrvid
Version: 0.5.3
Summary: CLI tool for OCR-ing video frames on macOS
Author: kj-9
License: Apache-2.0
Project-URL: Homepage, https://github.com/kj-9/ocrvid
Project-URL: Changelog, https://github.com/kj-9/ocrvid/releases
Project-URL: Issues, https://github.com/kj-9/ocrvid/issues
Project-URL: CI, https://github.com/kj-9/ocrvid/actions
Keywords: ocr,macos,video,movie,cli
Classifier: License :: OSI Approved :: Apache Software License
Classifier: Development Status :: 3 - Alpha
Classifier: Operating System :: MacOS :: MacOS X
Classifier: Topic :: Scientific/Engineering :: Image Recognition
Requires-Python: >=3.8
License-File: LICENSE
Requires-Dist: click
Requires-Dist: pyobjc-framework-Vision
Requires-Dist: opencv-python
Requires-Dist: pyserde <0.14
Provides-Extra: test
Requires-Dist: pre-commit ; extra == 'test'
Requires-Dist: pytest ; extra == 'test'
Requires-Dist: cogapp ; extra == 'test'
